Compiled from "SynchronizedDemo.java"
public class com.example.demo.primary.sync.SynchronizedDemo {
  public com.example.demo.primary.sync.SynchronizedDemo();
    Code:
       0: aload_0
       1: invokespecial #1                  // Method java/lang/Object."<init>":()V
       4: return

  public void method();
    Code:
       0: aload_0
       1: dup
       2: astore_1
       // 指令指向同步代码的开始位置
       3: monitorenter
       4: getstatic     #2                  // Field java/lang/System.out:Ljava/io/PrintStream;
       7: ldc           #3                  // String Method 1 start
       9: invokevirtual #4                  // Method java/io/PrintStream.println:(Ljava/lang/String;)V
      12: aload_1
      // monitorexit指令则指明同步代码块的结束位置
      13: monitorexit
      14: goto          22
      17: astore_2
      18: aload_1
      // 这是为了保证即便方法异常退出也能正确的释放锁
      19: monitorexit
      20: aload_2
      21: athrow
      22: return
    Exception table:
       from    to  target type
           4    14    17   any
          17    20    17   any
}
