Compiled from "Volatile是线程不安全的.java"
public class com.example.demo.primary.volatile学习.Volatile是线程不安全的 {
  public static volatile int race;

  public com.example.demo.primary.volatile学习.Volatile是线程不安全的();
    Code:
       0: aload_0
       1: invokespecial #1                  // Method java/lang/Object."<init>":()V
       4: return

  public static void increase();
    Code:
       0: getstatic     #2                  // Field race:I
       3: iconst_1
       4: iadd
       5: putstatic     #2                  // Field race:I
       8: getstatic     #3                  // Field java/lang/System.out:Ljava/io/PrintStream;
      11: new           #4                  // class java/lang/StringBuilder
      14: dup
      15: invokespecial #5                  // Method java/lang/StringBuilder."<init>":()V
      18: getstatic     #2                  // Field race:I
      21: invokevirtual #6                  // Method java/lang/StringBuilder.append:(I)Ljava/lang/StringBuilder;
      24: ldc           #7                  // String ++
      26: invokevirtual #8                  // Method java/lang/StringBuilder.append:(Ljava/lang/String;)Ljava/lang/StringBuilder;
      29: invokevirtual #9                  // Method java/lang/StringBuilder.toString:()Ljava/lang/String;
      32: invokevirtual #10                 // Method java/io/PrintStream.println:(Ljava/lang/String;)V
      35: return

  public static void main(java.lang.String[]);
    Code:
       0: getstatic     #3                  // Field java/lang/System.out:Ljava/io/PrintStream;
       3: ldc           #11                 // String ----------->
       5: invokevirtual #10                 // Method java/io/PrintStream.println:(Ljava/lang/String;)V
       8: iconst_0
       9: istore_1
      10: iload_1
      11: bipush        20
      13: if_icmpge     37
      16: new           #13                 // class java/lang/Thread
      19: dup
      20: invokedynamic #14,  0             // InvokeDynamic #0:run:()Ljava/lang/Runnable;
      25: invokespecial #15                 // Method java/lang/Thread."<init>":(Ljava/lang/Runnable;)V
      28: invokevirtual #16                 // Method java/lang/Thread.start:()V
      31: iinc          1, 1
      34: goto          10
      37: iconst_0
      38: istore_1
      39: invokestatic  #17                 // Method java/lang/Thread.activeCount:()I
      42: dup
      43: istore_1
      44: iconst_2
      45: if_icmple     79
      48: getstatic     #3                  // Field java/lang/System.out:Ljava/io/PrintStream;
      51: new           #4                  // class java/lang/StringBuilder
      54: dup
      55: invokespecial #5                  // Method java/lang/StringBuilder."<init>":()V
      58: ldc           #18                 // String 当前活跃线程数：
      60: invokevirtual #8                  // Method java/lang/StringBuilder.append:(Ljava/lang/String;)Ljava/lang/StringBuilder;
      63: iload_1
      64: invokevirtual #6                  // Method java/lang/StringBuilder.append:(I)Ljava/lang/StringBuilder;
      67: invokevirtual #9                  // Method java/lang/StringBuilder.toString:()Ljava/lang/String;
      70: invokevirtual #10                 // Method java/io/PrintStream.println:(Ljava/lang/String;)V
      73: invokestatic  #19                 // Method java/lang/Thread.yield:()V
      76: goto          39
      79: getstatic     #3                  // Field java/lang/System.out:Ljava/io/PrintStream;
      82: getstatic     #2                  // Field race:I
      85: invokevirtual #20                 // Method java/io/PrintStream.println:(I)V
      88: return

  static {};
    Code:
       0: iconst_0
       1: putstatic     #2                  // Field race:I
       4: return
}
